Metadata-Version: 2.1
Name: tap-signonsite
Version: 0.0.1
Summary: Singer.io tap for extracting data from the SignOnSite API
Home-page: https://samwoolerton.com
Author: Sam Woolerton
License: UNKNOWN
Platform: UNKNOWN
Classifier: Programming Language :: Python :: 3 :: Only
Requires-Python: >=3.6.0
Provides-Extra: dev
